insanic/__init__.py
insanic/app.py
insanic/blueprint.py
insanic/cli.py
insanic/commands/__init__.py
insanic/commands/migrations.py
insanic/commands/routes.py
insanic/commands/server.py
insanic/commands/tasks.py
insanic/config.py
insanic/db.py
insanic/forms/__init__.py
insanic/forms/fields.py
insanic/forms/forms.py
insanic/http.py
insanic/logger.py
insanic/py.typed
insanic/serializers/__init__.py
insanic/serializers/fields.py
insanic/serializers/serializers.py
insanic/tasks.py
insanic/utils.py
insanic/views.py
insanic-0.1.7.dist-info/WHEEL
insanic-0.1.7.dist-info/METADATA
insanic-0.1.7.dist-info/RECORD
