Metadata-Version: 2.1
Name: insanic
Version: 0.1.7
Summary: Django like web framework based on Sanic and TortoiseORM
Author: Dmitry Ovchinnikov
Author-email: mail@dimka.online
Requires-Python: >=3.10,<4.0
Classifier: Programming Language :: Python :: 3
Classifier: Programming Language :: Python :: 3.10
Requires-Dist: arq (>=0.22,<0.23)
Requires-Dist: asyncmy (>=0.2.3,<0.3.0)
Requires-Dist: cryptography (>=36.0.1,<37.0.0)
Requires-Dist: loguru (>=0.6.0,<0.7.0)
Requires-Dist: sanic (>=21.12.0,<22.0.0)
Requires-Dist: tortoise-orm (>=0.18.0,<0.19.0)
